smoacks/ApiClientBase.py
smoacks/ApiGenerator.py
smoacks/AppObject.py
smoacks/ConnexionApiGenerator.py
smoacks/MergeApis.py
smoacks/NoseTestGenerator.py
smoacks/OpenapiGenerator.py
smoacks/Property.py
smoacks/Schema.py
smoacks/ServerGenerator.py
smoacks/SqlAlchemyGenerator.py
smoacks/__init__.py
smoacks/api_util.py
smoacks/cli_util.py
smoacks/command_line.py
smoacks/sconfig.py
smoacks/structure.py
smoacks/util.py
smoacks-0.2.47.data/data/conf/smoacks_default.yaml
smoacks-0.2.47.data/data/templates/ClientApi.jinja
smoacks-0.2.47.data/data/templates/ConnexionApis.jinja
smoacks-0.2.47.data/data/templates/DataModel.jinja
smoacks-0.2.47.data/data/templates/DataModelObject.jinja
smoacks-0.2.47.data/data/templates/Dockerfile.jinja
smoacks-0.2.47.data/data/templates/ModelApis.jinja
smoacks-0.2.47.data/data/templates/NoseTests.jinja
smoacks-0.2.47.data/data/templates/SQLAlchemyModel.jinja
smoacks-0.2.47.data/data/templates/TestUtil.jinja
smoacks-0.2.47.data/data/templates/api_util.jinja
smoacks-0.2.47.data/data/templates/app-env.jinja
smoacks-0.2.47.data/data/templates/base.jinja
smoacks-0.2.47.data/data/templates/cli_add.jinja
smoacks-0.2.47.data/data/templates/cli_import.jinja
smoacks-0.2.47.data/data/templates/cli_search.jinja
smoacks-0.2.47.data/data/templates/dev-api-server.jinja
smoacks-0.2.47.data/data/templates/gitignore.jinja
smoacks-0.2.47.data/data/templates/local-env.jinja
smoacks-0.2.47.data/data/templates/login.jinja
smoacks-0.2.47.data/data/templates/schema.jinja
smoacks-0.2.47.data/data/templates/server-loop.jinja
smoacks-0.2.47.data/data/templates/server.jinja
smoacks-0.2.47.data/data/templates/server_logging.jinja
smoacks-0.2.47.data/data/templates/setup.jinja
smoacks-0.2.47.data/data/templates/shutdown.jinja
smoacks-0.2.47.data/data/templates/test-api-server.jinja
smoacks-0.2.47.data/data/templates/test-login-api.jinja
smoacks-0.2.47.data/data/templates/testme.jinja
smoacks-0.2.47.dist-info/LICENSE
smoacks-0.2.47.dist-info/METADATA
smoacks-0.2.47.dist-info/WHEEL
smoacks-0.2.47.dist-info/entry_points.txt
smoacks-0.2.47.dist-info/top_level.txt
smoacks-0.2.47.dist-info/RECORD
