Metadata-Version: 2.1
Name: smoacks
Version: 0.2.47
Summary: Simple Microservices with OpenAPI, Connexion, Kubernetes, and SQLAlchemy
Home-page: https://github.com/wittlesouth/smoacks
Author: Wittle South Ventures, LLC
Author-email: service@wittlesouth.com
License: UNKNOWN
Platform: UNKNOWN
Classifier: License :: OSI Approved :: MIT License
Classifier: Development Status :: 3 - Alpha
Classifier: Programming Language :: Python
Classifier: Topic :: Software Development :: Libraries
Requires-Dist: connexion
Requires-Dist: coverage
Requires-Dist: flask-jwt-extended
Requires-Dist: jinja2
Requires-Dist: nose
Requires-Dist: openapi-spec-validator
Requires-Dist: python-dateutil
Requires-Dist: PyYAML
Requires-Dist: SQLAlchemy
